shad4fast/__about__.py
shad4fast/__init__.py
shad4fast/cli.py
shad4fast/headers.py
shad4fast/components/__init__.py
shad4fast/components/accordion.py
shad4fast/components/alert.py
shad4fast/components/aspect_ratio.py
shad4fast/components/avatar.py
shad4fast/components/badge.py
shad4fast/components/breadcrumb.py
shad4fast/components/button.py
shad4fast/components/card.py
shad4fast/components/carousel.py
shad4fast/components/checkbox.py
shad4fast/components/collapsible.py
shad4fast/components/dialog.py
shad4fast/components/input.py
shad4fast/components/label.py
shad4fast/components/nav.py
shad4fast/components/progress.py
shad4fast/components/radio.py
shad4fast/components/scroll_area.py
shad4fast/components/select.py
shad4fast/components/separator.py
shad4fast/components/sheet.py
shad4fast/components/skeleton.py
shad4fast/components/slider.py
shad4fast/components/switch.py
shad4fast/components/table.py
shad4fast/components/tabs.py
shad4fast/components/textarea.py
shad4fast/components/toast.py
shad4fast/components/toggle.py
shad4fast/components/tooltip.py
shad4fast/js/main_scripts.js
shad4fast/js/theme.js
shad4fast-1.3.1.dist-info/METADATA
shad4fast-1.3.1.dist-info/WHEEL
shad4fast-1.3.1.dist-info/entry_points.txt
shad4fast-1.3.1.dist-info/licenses/LICENSE.txt
shad4fast-1.3.1.dist-info/RECORD
