Metadata-Version: 2.3
Name: Shad4Fast
Version: 1.3.1
Summary: Shadcn style components to be used with fasthtml
Project-URL: Documentation, https://github.com/curtis-allan/shad4fasthtml#readme
Project-URL: Issues, https://github.com/curtis-allan/shad4fasthtml/issues
Project-URL: Source, https://github.com/curtis-allan/shad4fasthtml
Author-email: Curtis Allan <curtisjallan98@gmail.com>
License: MIT
License-File: LICENSE.txt
Keywords: components,shadcn,tailwindcss,ui
Classifier: Development Status :: 4 - Beta
Classifier: Programming Language :: Python
Classifier: Programming Language :: Python :: 3.8
Classifier: Programming Language :: Python :: 3.9
Classifier: Programming Language :: Python :: 3.10
Classifier: Programming Language :: Python :: 3.11
Classifier: Programming Language :: Python :: 3.12
Classifier: Programming Language :: Python :: Implementation :: CPython
Classifier: Programming Language :: Python :: Implementation :: PyPy
Requires-Python: >=3.8
Requires-Dist: lucide-fasthtml>=0.0.6
Requires-Dist: python-fasthtml
